<?xml version="1.0" ?>
<FlowMonitor>
  <FlowStats>
    <Flow flowId="1" timeFirstTxPacket="+402500000.0ns" timeFirstRxPacket="+409247000.0ns" timeLastTxPacket="+49992500000.0ns" timeLastRxPacket="+49993012200.0ns" delaySum="+3174939400.0ns" jitterSum="+1039064000.0ns" lastDelay="+512200.0ns" txBytes="5217920" rxBytes="5217920" txPackets="4960" rxPackets="4960" lostPackets="0" timesForwarded="0">
      <delayHistogram nBins="7" >
        <bin index="0" start="0" width="0.001" count="4236" />
        <bin index="1" start="0.001" width="0.001" count="680" />
        <bin index="2" start="0.002" width="0.001" count="42" />
        <bin index="3" start="0.003" width="0.001" count="1" />
        <bin index="6" start="0.006" width="0.001" count="1" />
      </delayHistogram>
      <jitterHistogram nBins="6" >
        <bin index="0" start="0" width="0.001" count="4857" />
        <bin index="1" start="0.001" width="0.001" count="88" />
        <bin index="2" start="0.002" width="0.001" count="13" />
        <bin index="5" start="0.005" width="0.001" count="1" />
      </jitterHistogram>
      <packetSizeHistogram nBins="53" >
        <bin index="52" start="1040" width="20" count="4960" />
      </packetSizeHistogram>
      <flowInterruptionsHistogram nBins="0" >
      </flowInterruptionsHistogram>
    </Flow>
  </FlowStats>
  <Ipv4FlowClassifier>
    <Flow flowId="1" sourceAddress="10.1.1.2" destinationAddress="10.1.1.1" protocol="17" sourcePort="49153" destinationPort="9">
      <Dscp value="0x0" packets="4960" />
    </Flow>
  </Ipv4FlowClassifier>
  <Ipv6FlowClassifier>
  </Ipv6FlowClassifier>
  <FlowProbes>
    <FlowProbe index="0">
      <FlowStats  flowId="1" packets="4960" bytes="5217920" delayFromFirstProbeSum="+3174939400.0ns" >
      </FlowStats>
    </FlowProbe>
    <FlowProbe index="1">
    </FlowProbe>
    <FlowProbe index="2">
      <FlowStats  flowId="1" packets="4960" bytes="5217920" delayFromFirstProbeSum="+0.0ns" >
      </FlowStats>
    </FlowProbe>
    <FlowProbe index="3">
    </FlowProbe>
  </FlowProbes>
</FlowMonitor>
